[1,["26avEFyi9K45oEC3eCh8fa@6c48a"],["_textureSource"],["cc.SpriteFrame","cc.SpriteAtlas"],0,[[[{"name":"6","spriteFrames":["500","ceMnCrAYZNsLq2UjQap8zY@c12ab","501","ceMnCrAYZNsLq2UjQap8zY@5c37e","502","ceMnCrAYZNsLq2UjQap8zY@bad2e","503","ceMnCrAYZNsLq2UjQap8zY@2f2d0"]}],[1],0,[],[],[]],[[{"name":"503","rect":{"x":95,"y":101,"width":92,"height":98},"offset":{"x":-2,"y":-4},"originalSize":{"width":160,"height":160},"rotated":false,"capInsets":[0,0,0,0],"vertices":{"rawPosition":[],"indexes":[],"uv":[],"nuv":[],"minPos":{"x":0,"y":0,"z":0},"maxPos":{"x":0,"y":0,"z":0}},"packable":true,"pixelsToUnit":100,"pivot":{"x":0.5,"y":0.5},"meshType":0}],[0],0,[0],[0],[0]],[[{"name":"501","rect":{"x":1,"y":101,"width":92,"height":98},"offset":{"x":-2,"y":-4},"originalSize":{"width":160,"height":160},"rotated":false,"capInsets":[0,0,0,0],"vertices":{"rawPosition":[],"indexes":[],"uv":[],"nuv":[],"minPos":{"x":0,"y":0,"z":0},"maxPos":{"x":0,"y":0,"z":0}},"packable":true,"pixelsToUnit":100,"pivot":{"x":0.5,"y":0.5},"meshType":0}],[0],0,[0],[0],[0]],[[{"name":"502","rect":{"x":95,"y":1,"width":92,"height":98},"offset":{"x":-2,"y":-4},"originalSize":{"width":160,"height":160},"rotated":false,"capInsets":[0,0,0,0],"vertices":{"rawPosition":[],"indexes":[],"uv":[],"nuv":[],"minPos":{"x":0,"y":0,"z":0},"maxPos":{"x":0,"y":0,"z":0}},"packable":true,"pixelsToUnit":100,"pivot":{"x":0.5,"y":0.5},"meshType":0}],[0],0,[0],[0],[0]],[[{"name":"500","rect":{"x":1,"y":1,"width":92,"height":98},"offset":{"x":-2,"y":-4},"originalSize":{"width":160,"height":160},"rotated":false,"capInsets":[0,0,0,0],"vertices":{"rawPosition":[],"indexes":[],"uv":[],"nuv":[],"minPos":{"x":0,"y":0,"z":0},"maxPos":{"x":0,"y":0,"z":0}},"packable":true,"pixelsToUnit":100,"pivot":{"x":0.5,"y":0.5},"meshType":0}],[0],0,[0],[0],[0]]]]
